material_engineering_QBD/__init__.py
material_engineering_QBD/concentration.py
material_engineering_QBD/fermidirac.py
material_engineering_QBD/interpolation.py
material_engineering_QBD/numeric.py
material_engineering_QBD/profile.py
material_engineering_QBD/tools.py
material_engineering_QBD-0.0.33.dist-info/LICENSE
material_engineering_QBD-0.0.33.dist-info/METADATA
material_engineering_QBD-0.0.33.dist-info/WHEEL
material_engineering_QBD-0.0.33.dist-info/top_level.txt
material_engineering_QBD-0.0.33.dist-info/RECORD
